test/__init__.py
test/test_active_directory_api.py
test/test_active_directory_body.py
test/test_alert.py
test/test_alert_type_mute_body.py
test/test_alerts_api.py
test/test_bucket_policy_body.py
test/test_bucket_policy_json_body.py
test/test_bucket_policyjson_body.py
test/test_bucket_quota_body.py
test/test_client_group.py
test/test_client_group_rules.py
test/test_cluster_api.py
test/test_cluster_body.py
test/test_cluster_body1.py
test/test_default_net.py
test/test_default_network_api.py
test/test_drive.py
test/test_drive_api.py
test/test_drives_activate_body.py
test/test_drives_body.py
test/test_drives_deactivate_body.py
test/test_event.py
test/test_event_description.py
test/test_event_params.py
test/test_events_api.py
test/test_failure_domain.py
test/test_failure_domains_api.py
test/test_file_system.py
test/test_file_system_api.py
test/test_file_system_group.py
test/test_file_system_group_api.py
test/test_file_system_groups_body.py
test/test_file_system_groups_uid_body.py
test/test_file_system_object_storages.py
test/test_file_systems_body.py
test/test_file_systems_download_body.py
test/test_file_systems_uid_body.py
test/test_health_api.py
test/test_host.py
test/test_host_aws.py
test/test_host_os_info.py
test/test_host_os_info_drivers.py
test/test_host_resource.py
test/test_host_resource_data.py
test/test_host_resource_data_backend_endpoints.py
test/test_host_resource_data_nodes.py
test/test_host_resource_data_nodes0.py
test/test_host_resource_data_nodes1.py
test/test_hosts_activate_body.py
test/test_hosts_api.py
test/test_hosts_apply_body.py
test/test_hosts_body.py
test/test_hosts_deactivate_body.py
test/test_hosts_uid_body.py
test/test_inline_response200.py
test/test_inline_response2001.py
test/test_inline_response20010.py
test/test_inline_response20010_data.py
test/test_inline_response20011.py
test/test_inline_response20012.py
test/test_inline_response20013.py
test/test_inline_response20014.py
test/test_inline_response20014_data.py
wekarestapi-1.0.1.dist-info/METADATA
wekarestapi-1.0.1.dist-info/WHEEL
wekarestapi-1.0.1.dist-info/top_level.txt
wekarestapi-1.0.1.dist-info/RECORD
