Metadata-Version: 2.1
Name: wekarestapi
Version: 1.0.1
Summary: @weka-api
Home-page: UNKNOWN
Author-email: vince@weka.io
License: UNKNOWN
Keywords: Swagger,@weka-api
Platform: UNKNOWN
Requires-Dist: urllib3 (>=1.15)
Requires-Dist: six (>=1.10)
Requires-Dist: certifi
Requires-Dist: python-dateutil
